odoo/addons/sale_project_reimbursement_cost/README.rst
odoo/addons/sale_project_reimbursement_cost/__init__.py
odoo/addons/sale_project_reimbursement_cost/__manifest__.py
odoo/addons/sale_project_reimbursement_cost/demo/product_demo.xml
odoo/addons/sale_project_reimbursement_cost/i18n/es.po
odoo/addons/sale_project_reimbursement_cost/i18n/it.po
odoo/addons/sale_project_reimbursement_cost/i18n/sale_project_reimbursement_cost.pot
odoo/addons/sale_project_reimbursement_cost/models/__init__.py
odoo/addons/sale_project_reimbursement_cost/models/account_move_line.py
odoo/addons/sale_project_reimbursement_cost/models/product_template.py
odoo/addons/sale_project_reimbursement_cost/models/project_project.py
odoo/addons/sale_project_reimbursement_cost/readme/CONFIGURE.md
odoo/addons/sale_project_reimbursement_cost/readme/CONTEXT.md
odoo/addons/sale_project_reimbursement_cost/readme/CONTRIBUTORS.md
odoo/addons/sale_project_reimbursement_cost/readme/DESCRIPTION.md
odoo/addons/sale_project_reimbursement_cost/readme/USAGE.md
odoo/addons/sale_project_reimbursement_cost/static/description/icon.png
odoo/addons/sale_project_reimbursement_cost/static/description/index.html
odoo/addons/sale_project_reimbursement_cost/static/src/components/project_right_side_panel/project_right_side_panel.esm.js
odoo/addons/sale_project_reimbursement_cost/static/src/components/project_right_side_panel/project_right_side_panel.xml
odoo/addons/sale_project_reimbursement_cost/tests/__init__.py
odoo/addons/sale_project_reimbursement_cost/tests/test_reimbursement_cost.py
odoo/addons/sale_project_reimbursement_cost/views/product_template_views.xml
odoo/addons/sale_project_reimbursement_cost/views/sale_order_line_views.xml
odoo_addon_sale_project_reimbursement_cost-17.0.1.0.0.4.dist-info/METADATA
odoo_addon_sale_project_reimbursement_cost-17.0.1.0.0.4.dist-info/WHEEL
odoo_addon_sale_project_reimbursement_cost-17.0.1.0.0.4.dist-info/top_level.txt
odoo_addon_sale_project_reimbursement_cost-17.0.1.0.0.4.dist-info/RECORD
